{
  "name": "Elsie Nguyen",
  "age": 61,
  "address": {
    "street": "Lotoci Junction",
    "city": "Vebbaki",
    "state": "MD",
    "zip": "02859"
  },
  "contact": {
    "phone": "(429) 296-3389",
    "servicePhone": "800539673"
  },
  "birthday": "2003-09-26T09:26:52.290Z",
  "ip": "241.167.162.14",
  "foo": "bar",
  "profile": {
    "about": "Domow cansawuju wi ic padhowti ughaho iwci gunrip at wujeg bakguc riufuke herkulug lame reli bun zeskifus. Oblalabi ara hudja fetdabrod ru widazu fanukubu ufevi levsu fo kopapu hi du tin kuted opmihgi le desamavi. Jiz jiba cis jigwo ir cunen wumar oj guwukuwo gop vaz kozzacum. Piniw top ko pute gesawuw ehu nowribbor pih fizut so zolha od zuzaduh. Num soz misuzegiw gec ca lorot kajduame peco bucoliepa ru zutawapud bas bujjada awaoso ul saojofo men.",
    "bio": "Ma uwike aci linorfuw za wocip mad bamrafje ag selvitaw lavjibul zazenub rifil ki ni lafzo sukku jeju. Piju mohbugru za pim ifate ef ga vani iga cec nitehobib behka ufa nimmuuf jojsobeco sa. Gotug war sof vur ew karni sidibuir ih meh sol ful gewnub guoseiz fufpir abime. Fivdusewi ci wuhuc ideso devjen cah nu dopo jablennah hidra hil go lihwo ujucitev obsa rozguz fim. Sihom talzuv ine rovudhe monufojo sij oju zeringa akka cezzupi ebiuji vo loh ikike dun ijapo mu mukfun."
  },
  "apiKey": "0f172b883e6c68668eb9d26c0d55c731f6cf4f5395154122d3d8b0bd7e9a43a7",
  "currency": {
    "code": "LBP",
    "name": "Lebanon Pound"
  }
}